{
    "name": "Midnight",
    "header": {
        "fg-color": "#2A2A3D",
        "text-color": "#C9C9E0"
    },
    "toolbar": {
        "fg-color": "#252535",
        "tool-fg-color": "transparent",
        "tool-hover-color": "#35354A",
        "tool-inner-color": "#9D9DB8"
    },
    "main": {
        "fg-color": "#1E1E2E"
    },
    "table": {
        "fg-color": "transparent",
        "head-fg-color": "#2E2E45",
        "head-text-color": "#A0A0C0",
        "row-fg-color-1": "#232333",
        "row-fg-color-2": "#272738",
        "row-fg-color-selected": "#3D2F5A",
        "row-text-color": "#D0D0E8",
        "row-badge-fg-color-true": "#3A2E50",
        "row-badge-text-color-true": "#C8A8F0",
        "row-badge-fg-color-false": "#2A3040",
        "row-badge-text-color-false": "#90A8C8"
    },
    "form":{
        "fg-color": "#22223A",
        "input": {
            "fg-color": "#2C2C42",
            "border-color": "#4A4A6A",
            "text-color": "#D0D0E8",
            "placeholder-color": "#6A6A8A"
        },
        "checkbox": {
            "fg-color": "#9B72CF",
            "hover-color": "#9B72CF",
            "border-color": "#4A4A6A",
            "text-color": "#B0B0D0"
        },
        "combobox": {
            "fg-color": "#2C2C42",
            "border-color": "#4A4A6A",
            "button-color": "#3D3D58",
            "text-color": "#D0D0E8"
        },
        "button": {
            "primary-fg-color": "#6B4FA0",
            "primary-hover-color": "#7D5FB5",
            "primary-text-color": "#FFFFFF",
            "secondary-fg-color": "#3A3A52",
            "secondary-hover-color": "#4A4A65",
            "secondary-text-color": "#C0C0DC"
        }
    },
    "config-panel": {
        "fg-color": "#1A1A2E",
        "open-fg-color": "transparent",
        "open-hover-color": "#35354A",
        "open-inner-color": "#9D9DB8",
        "title-fg-color": "#2E2E45",
        "title-text-color": "#C8A8F0",
        "label-text-color": "#A0A0C0",
        "input-fg-color": "#2C2C42",
        "input-border-color": "#4A4A6A",
        "input-button-color": "#3D3D58",
        "input-text-color": "#D0D0E8",
        "button-fg-color": "#6B4FA0",
        "button-hover-color": "#7D5FB5",
        "button-text-color": "#FFFFFF"
    }
}